{
  "routes": [
    {
      "method": "GET",
      "path": "/cidades",
      "handler": "cidades.find",
      "config": {
        "policies": []
      }
    },
    {
      "method": "GET",
      "path": "/cidades/count",
      "handler": "cidades.count",
      "config": {
        "policies": []
      }
    },
    {
      "method": "GET",
      "path": "/cidades/:id",
      "handler": "cidades.findOne",
      "config": {
        "policies": []
      }
    },
    {
      "method": "POST",
      "path": "/cidades",
      "handler": "cidades.create",
      "config": {
        "policies": []
      }
    },
    {
      "method": "PUT",
      "path": "/cidades/:id",
      "handler": "cidades.update",
      "config": {
        "policies": []
      }
    },
    {
      "method": "DELETE",
      "path": "/cidades/:id",
      "handler": "cidades.delete",
      "config": {
        "policies": []
      }
    }
  ]
}
